sqlalchemy/__init__.py
sqlalchemy/events.py
sqlalchemy/exc.py
sqlalchemy/inspection.py
sqlalchemy/log.py
sqlalchemy/py.typed
sqlalchemy/schema.py
sqlalchemy/types.py
sqlalchemy/connectors/__init__.py
sqlalchemy/connectors/aioodbc.py
sqlalchemy/connectors/asyncio.py
sqlalchemy/connectors/pyodbc.py
sqlalchemy/dialects/__init__.py
sqlalchemy/dialects/_typing.py
sqlalchemy/dialects/type_migration_guidelines.txt
sqlalchemy/dialects/mssql/__init__.py
sqlalchemy/dialects/mssql/aioodbc.py
sqlalchemy/dialects/mssql/base.py
sqlalchemy/dialects/mssql/information_schema.py
sqlalchemy/dialects/mssql/json.py
sqlalchemy/dialects/mssql/provision.py
sqlalchemy/dialects/mssql/pymssql.py
sqlalchemy/dialects/mssql/pyodbc.py
sqlalchemy/dialects/mysql/__init__.py
sqlalchemy/dialects/mysql/aiomysql.py
sqlalchemy/dialects/mysql/asyncmy.py
sqlalchemy/dialects/mysql/base.py
sqlalchemy/dialects/mysql/cymysql.py
sqlalchemy/dialects/mysql/dml.py
sqlalchemy/dialects/mysql/enumerated.py
sqlalchemy/dialects/mysql/expression.py
sqlalchemy/dialects/mysql/json.py
sqlalchemy/dialects/mysql/mariadb.py
sqlalchemy/dialects/mysql/mariadbconnector.py
sqlalchemy/dialects/mysql/mysqlconnector.py
sqlalchemy/dialects/mysql/mysqldb.py
sqlalchemy/dialects/mysql/provision.py
sqlalchemy/dialects/mysql/pymysql.py
sqlalchemy/dialects/mysql/pyodbc.py
sqlalchemy/dialects/mysql/reflection.py
sqlalchemy/dialects/mysql/reserved_words.py
sqlalchemy/dialects/mysql/types.py
sqlalchemy/dialects/oracle/__init__.py
sqlalchemy/dialects/oracle/base.py
sqlalchemy/dialects/oracle/cx_oracle.py
sqlalchemy/dialects/oracle/dictionary.py
sqlalchemy/dialects/oracle/oracledb.py
sqlalchemy/dialects/oracle/provision.py
sqlalchemy/dialects/oracle/types.py
sqlalchemy/dialects/oracle/vector.py
sqlalchemy/dialects/postgresql/__init__.py
sqlalchemy/dialects/postgresql/_psycopg_common.py
sqlalchemy/dialects/postgresql/array.py
sqlalchemy/dialects/postgresql/asyncpg.py
sqlalchemy/dialects/postgresql/base.py
sqlalchemy_fnma-2.1.0b1.dev0.dist-info/licenses/LICENSE
sqlalchemy_fnma-2.1.0b1.dev0.dist-info/METADATA
sqlalchemy_fnma-2.1.0b1.dev0.dist-info/WHEEL
sqlalchemy_fnma-2.1.0b1.dev0.dist-info/top_level.txt
sqlalchemy_fnma-2.1.0b1.dev0.dist-info/RECORD
