Metadata-Version: 2.4
Name: sqlalchemy-fnma
Version: 2.1.0b1.dev0
Summary: Database Abstraction Library
Author-email: Mike Bayer <mike_mp@zzzcomputing.com>
License-Expression: MIT
Project-URL: Homepage, https://www.sqlalchemy.org
Project-URL: Documentation, https://docs.sqlalchemy.org
Project-URL: Changelog, https://docs.sqlalchemy.org/latest/changelog/index.html
Project-URL: Source Code, https://github.com/sqlalchemy/sqlalchemy
Project-URL: Issue Tracker, https://github.com/sqlalchemy/sqlalchemy/issues
Project-URL: Discussions, https://github.com/sqlalchemy/sqlalchemy/discussions
Classifier: Development Status :: 5 - Production/Stable
Classifier: Intended Audience :: Developers
Classifier: Operating System :: OS Independent
Classifier: Programming Language :: Python
Classifier: Programming Language :: Python :: 3
Classifier: Programming Language :: Python :: 3.10
Classifier: Programming Language :: Python :: 3.11
Classifier: Programming Language :: Python :: 3.12
Classifier: Programming Language :: Python :: 3.13
Classifier: Programming Language :: Python :: 3.14
Classifier: Programming Language :: Python :: Implementation :: CPython
Classifier: Programming Language :: Python :: Implementation :: PyPy
Classifier: Topic :: Database :: Front-Ends
Requires-Python: >=3.10
License-File: LICENSE
Requires-Dist: typing-extensions>=4.6.0
Provides-Extra: asyncio
Requires-Dist: greenlet>=1; extra == "asyncio"
Provides-Extra: mypy
Requires-Dist: mypy>=1.7; extra == "mypy"
Requires-Dist: types-greenlet>=2; extra == "mypy"
Provides-Extra: mssql
Requires-Dist: pyodbc; extra == "mssql"
Provides-Extra: mssql-pymssql
Requires-Dist: pymssql; extra == "mssql-pymssql"
Provides-Extra: mssql-pyodbc
Requires-Dist: pyodbc; extra == "mssql-pyodbc"
Provides-Extra: mysql
Requires-Dist: mysqlclient>=1.4.0; extra == "mysql"
Provides-Extra: mysql-connector
Requires-Dist: mysql-connector-python; extra == "mysql-connector"
Provides-Extra: mariadb-connector
Requires-Dist: mariadb!=1.1.10,!=1.1.2,!=1.1.5,>=1.0.1; extra == "mariadb-connector"
Provides-Extra: oracle
Requires-Dist: cx_oracle>=8; extra == "oracle"
Provides-Extra: oracle-oracledb
Requires-Dist: oracledb>=1.0.1; extra == "oracle-oracledb"
Provides-Extra: postgresql
Requires-Dist: psycopg2>=2.7; extra == "postgresql"
Provides-Extra: postgresql-pg8000
Requires-Dist: pg8000>=1.29.3; extra == "postgresql-pg8000"
Provides-Extra: postgresql-asyncpg
Requires-Dist: sqlalchemy[asyncio]; extra == "postgresql-asyncpg"
Requires-Dist: asyncpg; extra == "postgresql-asyncpg"
Provides-Extra: postgresql-psycopg2binary
Requires-Dist: psycopg2-binary; extra == "postgresql-psycopg2binary"
Provides-Extra: postgresql-psycopg2cffi
Requires-Dist: psycopg2cffi; extra == "postgresql-psycopg2cffi"
Provides-Extra: postgresql-psycopg
Requires-Dist: psycopg!=3.1.15,>=3.0.7; extra == "postgresql-psycopg"
Provides-Extra: postgresql-psycopgbinary
Requires-Dist: psycopg[binary]!=3.1.15,>=3.0.7; extra == "postgresql-psycopgbinary"
Provides-Extra: pymysql
Requires-Dist: pymysql; extra == "pymysql"
Provides-Extra: cymysql
Requires-Dist: cymysql; extra == "cymysql"
Provides-Extra: aiomysql
Requires-Dist: sqlalchemy[asyncio]; extra == "aiomysql"
Requires-Dist: aiomysql; extra == "aiomysql"
Provides-Extra: aioodbc
Requires-Dist: sqlalchemy[asyncio]; extra == "aioodbc"
Requires-Dist: aioodbc; extra == "aioodbc"
Provides-Extra: asyncmy
Requires-Dist: sqlalchemy[asyncio]; extra == "asyncmy"
Requires-Dist: asyncmy!=0.2.4,!=0.2.6,>=0.2.3; extra == "asyncmy"
Provides-Extra: aiosqlite
Requires-Dist: sqlalchemy[asyncio]; extra == "aiosqlite"
Requires-Dist: aiosqlite; extra == "aiosqlite"
Provides-Extra: sqlcipher
Requires-Dist: sqlcipher3_binary; extra == "sqlcipher"
Provides-Extra: mssql-pymssql
Requires-Dist: sqlalchemy[mssql-pymssql]; extra == "mssql-pymssql"
Provides-Extra: mssql-pyodbc
Requires-Dist: sqlalchemy[mssql-pyodbc]; extra == "mssql-pyodbc"
Provides-Extra: mysql-connector
Requires-Dist: sqlalchemy[mysql-connector]; extra == "mysql-connector"
Provides-Extra: mariadb-connector
Requires-Dist: sqlalchemy[mariadb-connector]; extra == "mariadb-connector"
Provides-Extra: oracle-oracledb
Requires-Dist: sqlalchemy[oracle-oracledb]; extra == "oracle-oracledb"
Provides-Extra: postgresql-pg8000
Requires-Dist: sqlalchemy[postgresql-pg8000]; extra == "postgresql-pg8000"
Provides-Extra: postgresql-asyncpg
Requires-Dist: sqlalchemy[postgresql-asyncpg]; extra == "postgresql-asyncpg"
Provides-Extra: postgresql-psycopg2binary
Requires-Dist: sqlalchemy[postgresql-psycopg2binary]; extra == "postgresql-psycopg2binary"
Provides-Extra: postgresql-psycopg2cffi
Requires-Dist: sqlalchemy[postgresql-psycopg2cffi]; extra == "postgresql-psycopg2cffi"
Provides-Extra: postgresql-psycopg
Requires-Dist: sqlalchemy[postgresql-psycopg]; extra == "postgresql-psycopg"
Provides-Extra: postgresql-psycopgbinary
Requires-Dist: sqlalchemy[postgresql-psycopgbinary]; extra == "postgresql-psycopgbinary"
Dynamic: license-file
